LICENSE
MANIFEST.in
README.md
VERSION
setup.cfg
setup.py
lazylog/__init__.py
lazylog.egg-info/PKG-INFO
lazylog.egg-info/SOURCES.txt
lazylog.egg-info/dependency_links.txt
lazylog.egg-info/top_level.txt