Metadata-Version: 2.1
Name: lazylog
Version: 0.2.13
Summary: Yet another python logger that simplifies json file logging and prettifies console output
Home-page: http://lazylog.readthedocs.io/en/latest/
Author: Andreas Bontozoglou
Author-email: bodozoglou@gmail.com
License: UNKNOWN
Download-URL: https://github.com/urban-1/lazylog/archive/master.tar.gz
Project-URL: Source, https://github.com/urban-1/lazylog
Project-URL: Documentation, http://lazylog.readthedocs.io/en/latest/
Project-URL: Tracker, https://github.com/urban-1/lazylog/issues
Keywords: logging,color,logfile,json
Platform: UNKNOWN
Classifier: Development Status :: 4 - Beta
Classifier: Environment :: Console
Classifier: Topic :: System :: Logging
Classifier: Intended Audience :: Developers
Classifier: License :: OSI Approved :: MIT License
Classifier: Programming Language :: Python :: 2.7
Classifier: Programming Language :: Python :: 3.4
Classifier: Programming Language :: Python :: 3.5
Classifier: Programming Language :: Python :: 3.6
